LICENSE.txt
MANIFEST.in
README.md
setup.py
bin/thania_helper_mysql_get_db_size.py
thaniya_client/AbstractBackupConnector.py
thaniya_client/AbstractTargetDirectoryStrategy.py
thaniya_client/AbstractThaniyaTask.py
thaniya_client/BackupClient_ThaniyaSSH.py
thaniya_client/BackupConnector_CIFSMount.py
thaniya_client/BackupConnector_DebugWrapper.py
thaniya_client/BackupConnector_Local.py
thaniya_client/BackupConnector_SSHMount.py
thaniya_client/EnumTarPathMode.py
thaniya_client/ProcessingContext.py
thaniya_client/TargetDirectoryStrategy_DateDefault.py
thaniya_client/TargetDirectoryStrategy_StaticDir.py
thaniya_client/ThaniyaBackupContext.py
thaniya_client/ThaniyaBackupDriver.py
thaniya_client/ThaniyaIO.py
thaniya_client/ThaniyaMySQL.py
thaniya_client/ThaniyaMySQL_native.py
thaniya_client/ThaniyaService.py
thaniya_client/ThaniyaTar.py
thaniya_client/ThaniyaTask_BackupDevice.py
thaniya_client/ThaniyaTask_BackupDir.py
thaniya_client/ThaniyaTask_BackupMediaWiki.py
thaniya_client/ThaniyaTask_BackupMediaWiki_User.py
thaniya_client/ThaniyaTask_BackupTypo3.py
thaniya_client/ThaniyaTask_BackupWordPress.py
thaniya_client/__init__.py
thaniya_client/constants.py
thaniya_client.egg-info/PKG-INFO
thaniya_client.egg-info/SOURCES.txt
thaniya_client.egg-info/dependency_links.txt
thaniya_client.egg-info/not-zip-safe
thaniya_client.egg-info/requires.txt
thaniya_client.egg-info/top_level.txt
thaniya_client/utils/ServiceInfo.py
thaniya_client/utils/ServiceMgr.py
thaniya_client/utils/__init__.py
thaniya_client/utils/temp.py