Metadata-Version: 2.1
Name: thaniya-client
Version: 0.2020.3.11.4
Summary: This python module implements the Thania Backup Client.
Home-page: https://github.com/jkpubsrc/python-module-thaniya-client
Author: Jürgen Knauth
Author-email: pubsrc@binary-overflow.de
License: Apache 2.0
Download-URL: https://github.com/jkpubsrc/python-module-thaniya-client/tarball/0.2020.3.11.4
Keywords: backup
Platform: UNKNOWN
Classifier: Development Status :: 4 - Beta
Classifier: License :: OSI Approved :: Apache Software License
